{
 "generated": "2026-06-01T15:30:26.343226+00:00",
 "prices": {
  "BZ=F": {
   "label": "Brent Crude",
   "symbol": "BZ=F",
   "price": 97.16,
   "change": 5.11,
   "change_pct": 5.55,
   "spark": [
    94.29000091552734,
    93.70999908447266,
    92.05000305175781,
    97.16000366210938
   ]
  },
  "CL=F": {
   "label": "WTI Crude",
   "symbol": "CL=F",
   "price": 93.97,
   "change": 6.61,
   "change_pct": 7.57,
   "spark": [
    88.68000030517578,
    88.9000015258789,
    87.36000061035156,
    93.97000122070312
   ]
  },
  "GC=F": {
   "label": "Gold",
   "symbol": "GC=F",
   "price": 4496.1,
   "change": -64.4,
   "change_pct": -1.41,
   "spark": [
    4447.5,
    4499.2998046875,
    4560.5,
    4496.10009765625
   ]
  },
  "DX-Y.NYB": {
   "label": "USD Index",
   "symbol": "DX-Y.NYB",
   "price": 99.28,
   "change": 0.37,
   "change_pct": 0.38,
   "spark": [
    99.20999908447266,
    99.0199966430664,
    98.91000366210938,
    99.28199768066406
   ]
  },
  "^GSPC": {
   "label": "S&P 500",
   "symbol": "^GSPC",
   "price": 7579.84,
   "change": -0.22,
   "change_pct": -0.0,
   "spark": [
    7519.1201171875,
    7520.35986328125,
    7563.6298828125,
    7580.06005859375,
    7579.83984375
   ]
  },
  "USO": {
   "label": "USO (Oil ETF)",
   "symbol": "USO",
   "price": 137.44,
   "change": 8.35,
   "change_pct": 6.47,
   "spark": [
    137.0,
    131.02999877929688,
    130.77999877929688,
    129.08999633789062,
    137.44000244140625
   ]
  },
  "^VIX": {
   "label": "VIX",
   "symbol": "^VIX",
   "price": 16.05,
   "change": 0.73,
   "change_pct": 4.77,
   "spark": [
    17.010000228881836,
    16.290000915527344,
    15.739999771118164,
    15.319999694824219,
    16.049999237060547
   ]
  },
  "NG=F": {
   "label": "Nat Gas",
   "symbol": "NG=F",
   "price": 3.17,
   "change": -0.12,
   "change_pct": -3.59,
   "spark": [
    3.0399999618530273,
    3.2850000858306885,
    3.2899999618530273,
    3.171999931335449
   ]
  }
 },
 "treaties": [
  {
   "name": "JCPOA — Iran Nuclear Deal",
   "parties": [
    "Iran",
    "P5+1"
   ],
   "signed": "2015-07-14",
   "status": "COLLAPSED",
   "last_event": "2018-05-08",
   "notes": "US withdrew unilaterally May 2018. Iran began exceeding limits in 2019. Indirect talks have stalled."
  },
  {
   "name": "Israel–Hezbollah Ceasefire (Nov 2024)",
   "parties": [
    "Israel",
    "Hezbollah",
    "Lebanon (mediator: US/France)"
   ],
   "signed": "2024-11-27",
   "status": "UNCERTAIN",
   "last_event": "2026-05-26",
   "notes": "60-day initial period with phased IDF withdrawal. Both sides report intermittent violations; broader picture stays largely in force."
  },
  {
   "name": "Iran–Saudi Diplomatic Restoration",
   "parties": [
    "Iran",
    "Saudi Arabia (mediator: China)"
   ],
   "signed": "2023-03-10",
   "status": "HOLDING",
   "last_event": "2026-04-01",
   "notes": "Beijing-brokered rapprochement; embassies reopened. Tensions persist over proxy conflicts."
  },
  {
   "name": "Israel–UAE Abraham Accords",
   "parties": [
    "Israel",
    "UAE",
    "Bahrain",
    "Morocco",
    "Sudan"
   ],
   "signed": "2020-09-15",
   "status": "HOLDING",
   "last_event": "2026-03-01",
   "notes": "Normalization holds but Gaza war has cooled engagement; Saudi accession deferred indefinitely."
  },
  {
   "name": "Yemen Truce (UN-mediated)",
   "parties": [
    "Houthi (Ansar Allah)",
    "Saudi-led coalition"
   ],
   "signed": "2022-04-02",
   "status": "EXPIRED",
   "last_event": "2022-10-02",
   "notes": "Formal 6-month truce lapsed Oct 2022. De facto pause held until Red Sea Houthi campaign restarted late 2023."
  },
  {
   "name": "Houthi Red Sea Ceasefire (US-Oman)",
   "parties": [
    "Houthi (Ansar Allah)",
    "United States"
   ],
   "signed": "2025-05-06",
   "status": "VIOLATED",
   "last_event": "2026-04-10",
   "notes": "US-Houthi de-escalation excluded Israel-bound vessels; Houthi missile strikes on Israel continued."
  },
  {
   "name": "Iran–Iraq Border Security Agreement",
   "parties": [
    "Iran",
    "Iraq"
   ],
   "signed": "2023-03-19",
   "status": "HOLDING",
   "last_event": "2026-02-15",
   "notes": "Bilateral agreement on Kurdish armed groups along Iran-Iraq border; cooperation deepens."
  },
  {
   "name": "Egypt–Israel Peace Treaty",
   "parties": [
    "Egypt",
    "Israel"
   ],
   "signed": "1979-03-26",
   "status": "HOLDING",
   "last_event": "2026-05-01",
   "notes": "Longest-standing Arab-Israeli treaty; under significant strain from Gaza war but holding."
  },
  {
   "name": "Jordan–Israel Peace Treaty",
   "parties": [
    "Jordan",
    "Israel"
   ],
   "signed": "1994-10-26",
   "status": "HOLDING",
   "last_event": "2026-04-15",
   "notes": "Diplomatic ties strained over Gaza; ambassador recalls have occurred but treaty intact."
  }
 ],
 "incidents": [
  {
   "title": "Iran freezes talks with US over Israeli military action in Lebanon, IRGC-affiliated outlet claims",
   "link": "https://www.jpost.com/middle-east/iran-news/article-898007",
   "source": "Jerusalem Post",
   "published": "2026-06-01T16:35:43+00:00",
   "severity": "low"
  },
  {
   "title": "Iran's new regulations govern Strait of Hormuz; foreign interference intolerable: Senior diplomat",
   "link": "https://presstv.ir/Detail/2026/06/01/769632/Iran-new-regulations-Hormuz-Oman-United-States",
   "source": "Press TV",
   "published": "2026-06-01T15:29:38.220570+00:00",
   "severity": "low"
  },
  {
   "title": "IRGC Navy approves transit of 15 ships via Hormuz Strait in past 24 hours",
   "link": "https://presstv.ir/Detail/2026/06/01/769654/IRGC-Navy-coordinates-passage-15-ships-Strait-of-Hormuz-",
   "source": "Press TV",
   "published": "2026-06-01T15:29:38.219627+00:00",
   "severity": "info"
  },
  {
   "title": "Pezeshkian: Iran committed to diplomacy, ready to ensure shipping security in Strait of Hormuz",
   "link": "https://en.irna.ir/news/86170617/Pezeshkian-Iran-committed-to-diplomacy-ready-to-ensure-shipping",
   "source": "IRNA",
   "published": "2026-06-01T14:53:30+00:00",
   "severity": "info"
  },
  {
   "title": "Russia-linked tanker seized, SCOTUS midterm impact, Colombia and BTS tickets reut.rs/4x0sTzV",
   "link": "https://bsky.app/profile/reuters.com/post/3mnadbyjsw62r",
   "source": "@reuters",
   "published": "2026-06-01T14:50:14+00:00",
   "severity": "high"
  },
  {
   "title": "Iran is stopping message exchanges with U.S., may block Hormuz, Tasnim news agency says",
   "link": "https://www.reddit.com/r/worldnews/comments/1ttu2e5/iran_is_stopping_message_exchanges_with_us_may/",
   "source": "r/worldnews",
   "published": "2026-06-01T14:32:33+00:00",
   "severity": "info"
  },
  {
   "title": "Maritime leaders say US-Iran peace deal must provide clear framework for Strait of Hormuz transit",
   "link": "https://www.jpost.com/international/article-897988",
   "source": "Jerusalem Post",
   "published": "2026-06-01T14:27:17+00:00",
   "severity": "info"
  },
  {
   "title": "Iran stops negotiations with U.S., vows to 'completely' block Strait of Hormuz: State media",
   "link": "https://www.reddit.com/r/geopolitics/comments/1ttti36/iran_stops_negotiations_with_us_vows_to/",
   "source": "r/geopolitics",
   "published": "2026-06-01T14:13:35+00:00",
   "severity": "info"
  },
  {
   "title": "Iran is stopping message exchanges with U.S., may block Hormuz, Tasnim news agency says",
   "link": "https://www.al-monitor.com/originals/2026/06/iran-stopping-message-exchanges-us-may-block-hormuz-tasnim-news-agency-says",
   "source": "Al-Monitor",
   "published": "2026-06-01T14:02:57+00:00",
   "severity": "info"
  },
  {
   "title": "Ship operators urge clear rules to return Hormuz to normal reut.rs/4u5AQBa",
   "link": "https://bsky.app/profile/reuters.com/post/3mnaaksdav22j",
   "source": "@reuters",
   "published": "2026-06-01T14:01:28+00:00",
   "severity": "info"
  },
  {
   "title": "Iran freezing exchange of messages with US over Israeli attacks in Lebanon – Tasnim",
   "link": "https://www.timesofisrael.com/iran-freezing-exchange-of-messages-with-us-over-israeli-attacks-in-lebanon-tasnim/",
   "source": "Times of Israel",
   "published": "2026-06-01T13:55:46+00:00",
   "severity": "medium"
  },
  {
   "title": "Iran stops negotiations with U.S., vows to 'completely' block Strait of Hormuz: State media",
   "link": "https://www.reddit.com/r/worldnews/comments/1ttsuq3/iran_stops_negotiations_with_us_vows_to/",
   "source": "r/worldnews",
   "published": "2026-06-01T13:50:34+00:00",
   "severity": "info"
  },
  {
   "title": "US says it struck Iranian radar sites as Iran targets American forces in Kuwait",
   "link": "https://www.bbc.com/news/articles/crlpy8n7pr6o?at_medium=RSS&at_campaign=rss",
   "source": "BBC Middle East",
   "published": "2026-06-01T13:12:26+00:00",
   "severity": "critical"
  },
  {
   "title": "Kremlin outraged by detention of Russian shadow fleet tanker, calls it \"piracy\"",
   "link": "https://www.reddit.com/r/worldnews/comments/1ttqypf/kremlin_outraged_by_detention_of_russian_shadow/",
   "source": "r/worldnews",
   "published": "2026-06-01T12:39:48+00:00",
   "severity": "info"
  },
  {
   "title": "Ethiopia began voting in a general election on Monday. The vote comes at a critical moment for the country, which faces fears of renewed conflict in the Tigray region and tensions with Eritrea over access to the Red Sea. Here's what to know.",
   "link": "https://bsky.app/profile/nytimes.com/post/3mna2dkreyr2y",
   "source": "@nytimes",
   "published": "2026-06-01T12:10:03.290200+00:00",
   "severity": "info"
  }
 ],
 "chokepoints": [
  {
   "name": "Strait of Hormuz",
   "description": "20% of global oil + LNG transit. Iran-controlled north shore.",
   "status": "ACTIVE",
   "incident_count": 9,
   "recent": [
    {
     "title": "Iran's new regulations govern Strait of Hormuz; foreign interference intolerable: Senior diplomat",
     "link": "https://presstv.ir/Detail/2026/06/01/769632/Iran-new-regulations-Hormuz-Oman-United-States",
     "source": "Press TV",
     "published": "2026-06-01T15:29:38.220570+00:00",
     "severity": "low"
    },
    {
     "title": "IRGC Navy approves transit of 15 ships via Hormuz Strait in past 24 hours",
     "link": "https://presstv.ir/Detail/2026/06/01/769654/IRGC-Navy-coordinates-passage-15-ships-Strait-of-Hormuz-",
     "source": "Press TV",
     "published": "2026-06-01T15:29:38.219627+00:00",
     "severity": "info"
    },
    {
     "title": "Pezeshkian: Iran committed to diplomacy, ready to ensure shipping security in Strait of Hormuz",
     "link": "https://en.irna.ir/news/86170617/Pezeshkian-Iran-committed-to-diplomacy-ready-to-ensure-shipping",
     "source": "IRNA",
     "published": "2026-06-01T14:53:30+00:00",
     "severity": "info"
    }
   ]
  },
  {
   "name": "Bab el-Mandeb / Red Sea",
   "description": "Suez canal southern approach. Houthi attack zone since late 2023.",
   "status": "ACTIVE",
   "incident_count": 1,
   "recent": [
    {
     "title": "Ethiopia began voting in a general election on Monday. The vote comes at a critical moment for the country, which faces fears of renewed conflict in the Tigray region and tensions with Eritrea over access to the Red Sea. Here's what to know.",
     "link": "https://bsky.app/profile/nytimes.com/post/3mna2dkreyr2y",
     "source": "@nytimes",
     "published": "2026-06-01T12:10:03.290200+00:00",
     "severity": "info"
    }
   ]
  },
  {
   "name": "Suez Canal",
   "description": "12% of global trade. Re-routings via Cape add ~10 days transit.",
   "status": "QUIET",
   "incident_count": 0,
   "recent": []
  },
  {
   "name": "Eastern Mediterranean",
   "description": "Israeli ports + Levantine gas fields. Hezbollah cross-border range.",
   "status": "QUIET",
   "incident_count": 0,
   "recent": []
  }
 ],
 "wh_statements": [
  {
   "id": "5b74dca04f25",
   "title": "It's official: Tina Peters, the former clerk convicted of participating in a scheme to chase election conspiracies pushed by Trump, has just been released from prison after Trump successfully pressured Colorado's Democratic governor into commuting her sentence, according to the AP.",
   "link": "https://bsky.app/profile/kylegriffin1.bsky.social/post/3mnafbv57g22r",
   "summary": "",
   "source": "@kylegriffin1",
   "category": "trump_bsky",
   "published": "2026-06-01T15:25:58.257+00:00",
   "iran_topic": false
  },
  {
   "id": "d5529c907861",
   "title": "‘So Selfish!’ Ex-Biden Aides Trash New Jill Biden Book — Accuse Her of Being ‘Disingenuous’",
   "link": "https://www.mediaite.com/media/news/so-selfish-ex-biden-aides-trash-new-jill-biden-book-accuse-her-of-being-disingenuous/",
   "summary": "Jill Biden’s new White House memoir is drawing fierce criticism from ex-Biden aides angrily accusing her of reopening painful divisions. The post ‘So Selfish!’ Ex-Biden Aides Trash New Jill Biden Book — Accuse Her of Being ‘Disingenuous’ first appeared on Mediaite .",
   "source": "Mediaite (all)",
   "category": "mediaite_all",
   "published": "2026-06-01T15:19:27+00:00",
   "iran_topic": false
  },
  {
   "id": "282590dd61b0",
   "title": "Iranian State Media Says Talks With US Suspended as Missiles Fired at US Forces During Ceasefire",
   "link": "https://www.mediaite.com/media/news/iranian-state-media-says-talks-with-us-suspended-as-missiles-fired-at-us-forces-during-ceasefire/",
   "summary": "\"So the reaction from Iran is to say: no more talks. They're also saying that they're going to completely close down the Strait of Hormuz\" The post Iranian State Media Says Talks With US Suspended as Missiles Fired at US Forces During Ceasefire first appeared on Mediaite .",
   "source": "Mediaite (all)",
   "category": "mediaite_all",
   "published": "2026-06-01T15:05:56+00:00",
   "iran_topic": true
  },
  {
   "id": "00e910ae9926",
   "title": "‘Just Stop It!’ CNN Data Guru Reveals More Americans Think the Earth Is Flat Than Approve of Trump Vanity Projects",
   "link": "https://www.mediaite.com/media/news/just-stop-it-cnn-data-guru-reveals-more-americans-think-the-earth-is-flat-than-approve-of-trump-vanity-projects/",
   "summary": "Harry Enten presented a shocking statistic about American sentiment toward President Donald Trump's vanity projects, including slapping his name on buildings. The post ‘Just Stop It!’ CNN Data Guru Reveals More Americans Think the Earth Is Flat Than Approve of Trump Vanity Projects first appeared on Mediaite .",
   "source": "Mediaite (all)",
   "category": "mediaite_all",
   "published": "2026-06-01T15:04:06+00:00",
   "iran_topic": false
  },
  {
   "id": "0845c36a4f09",
   "title": "Republican Bashes Trump ‘Slush Fund’ on Fox: ‘As the Wife of a First Responder…’",
   "link": "https://www.mediaite.com/media/news/republican-bashes-trump-slush-fund-on-fox-as-the-wife-of-a-first-responder/",
   "summary": "Rep. Kat Cammack (R-FL) bashed President Donald Trump's anti-weaponization fund on Monday, telling Fox Business host Cheryl Casone that the move amounted to \"throwing money at the problem.\" The post Republican Bashes Trump ‘Slush Fund’ on Fox: ‘As the Wife of a First Responder…’ first appeared on Mediaite .",
   "source": "Mediaite (all)",
   "category": "mediaite_all",
   "published": "2026-06-01T14:51:59+00:00",
   "iran_topic": false
  },
  {
   "id": "9415ed24ec99",
   "title": "‘Made-Up Numbers’: Jimmy Kimmel Disputes Report Stephen Colbert Was Losing $40 Million a Year",
   "link": "https://www.mediaite.com/media/made-up-numbers-jimmy-kimmel-disputes-report-stephen-colbert-was-losing-40-million-a-year/",
   "summary": "Jimmy Kimmel said he is not buying that his friend and former late night competitor Stephen Colbert was losing tens of millions of dollars per year for CBS. The post ‘Made-Up Numbers’: Jimmy Kimmel Disputes Report Stephen Colbert Was Losing $40 Million a Year first appeared on Mediaite .",
   "source": "Mediaite (all)",
   "category": "mediaite_all",
   "published": "2026-06-01T14:42:03+00:00",
   "iran_topic": false
  },
  {
   "id": "04bb0d676720",
   "title": "WATCH: College Baseball Player Ejected for Home Run Celebration in Chaotic Scene",
   "link": "https://www.mediaite.com/media/sports/watch-college-baseball-player-ejected-for-home-run-celebration-in-chaotic-scene/",
   "summary": "A player from the University of Georgia baseball team was ejected Sunday for the way he celebrated a crucial go-ahead home run. The post WATCH: College Baseball Player Ejected for Home Run Celebration in Chaotic Scene first appeared on Mediaite .",
   "source": "Mediaite (all)",
   "category": "mediaite_all",
   "published": "2026-06-01T14:20:10+00:00",
   "iran_topic": false
  },
  {
   "id": "1a2a7dd07bb5",
   "title": "‘Another Masterstroke by the President!’ House Republican Falls All Over Himself to Praise Trump on Iran",
   "link": "https://www.mediaite.com/media/tv/another-masterstroke-by-the-president-house-republican-falls-all-over-himself-to-praise-trump-on-iran/",
   "summary": "Rep. Riley Moore claimed the still-unfinished agreement to continue the ceasefire would \"go down in the history books as one of the great peace deals\" Trump has done. The post ‘Another Masterstroke by the President!’ House Republican Falls All Over Himself to Praise Trump on Iran first appeared on Mediaite .",
   "source": "Mediaite (all)",
   "category": "mediaite_all",
   "published": "2026-06-01T14:15:52+00:00",
   "iran_topic": true
  },
  {
   "id": "3abbbdb6900f",
   "title": "Enten: \"So fewer Americans think it's acceptable to put President Trump's name on government buildings right now than believe that the earth is that or the moon landing is fake\"",
   "link": "https://bsky.app/profile/atrupar.com/post/3mnaanjo2h62f",
   "summary": "",
   "source": "@atrupar",
   "category": "trump_bsky",
   "published": "2026-06-01T14:03:00.154+00:00",
   "iran_topic": false
  },
  {
   "id": "70401a58c459",
   "title": "‘Wipeout!’ Mark Halperin Reports Republicans Are Going ‘Bonkers’ Watching Trump ‘Screw’ Up the Midterms",
   "link": "https://www.mediaite.com/media/podcasts/wipeout-mark-halperin-reports-republicans-are-going-bonkers-watching-trump-screw-up-the-midterms/",
   "summary": "Mark Halperin reported that President Donald Trump is driving his fellow Republicans \"bonkers\" by setting them up for a midterm \"wipeout.\" The post ‘Wipeout!’ Mark Halperin Reports Republicans Are Going ‘Bonkers’ Watching Trump ‘Screw’ Up the Midterms first appeared on Mediaite .",
   "source": "Mediaite (all)",
   "category": "mediaite_all",
   "published": "2026-06-01T13:56:34+00:00",
   "iran_topic": false
  },
  {
   "id": "84d929df1517",
   "title": "Rep. Sheri Biggs: \"We have to put America first, and as I've said before, if you don't love this country, get out\"",
   "link": "https://bsky.app/profile/atrupar.com/post/3mnaa2jqqab2p",
   "summary": "",
   "source": "@atrupar",
   "category": "trump_bsky",
   "published": "2026-06-01T13:52:22.702+00:00",
   "iran_topic": false
  },
  {
   "id": "cb4e4ed68b06",
   "title": "The bleaker things get, the more outrageous their bootlicking becomes.",
   "link": "https://bsky.app/profile/zanath.bsky.social/post/3mna7ybe4n22t",
   "summary": "",
   "source": "@zanath",
   "category": "trump_bsky",
   "published": "2026-06-01T13:51:06.812+00:00",
   "iran_topic": false
  },
  {
   "id": "aa6544c899a6",
   "title": "Rep. Sheri Biggs on Iran. \"I think we have to trust him. The American people elected President Trump for a reason, and it's because he has the backbone, the intelligence to get things done.\"",
   "link": "https://bsky.app/profile/atrupar.com/post/3mna7v7fbck2j",
   "summary": "",
   "source": "@atrupar",
   "category": "trump_bsky",
   "published": "2026-06-01T13:49:23.969+00:00",
   "iran_topic": true
  },
  {
   "id": "25d89e8d6a1e",
   "title": "Sen. Bill Hagerty: \"This economy is humming\"",
   "link": "https://bsky.app/profile/atrupar.com/post/3mna7hulal42v",
   "summary": "",
   "source": "@atrupar",
   "category": "trump_bsky",
   "published": "2026-06-01T13:41:56.526+00:00",
   "iran_topic": false
  },
  {
   "id": "c526c3e59221",
   "title": "Satellite Imagery Shows Iran’s Speedy Recovery After US Strikes: Report",
   "link": "https://www.mediaite.com/media/news/satellite-imagery-shows-irans-speedy-recovery-after-us-strikes-report/",
   "summary": "Iran quickly recovered long-range missiles buried by U.S. strikes, using bulldozers and dump trucks to quickly regain access to underground sites, according to satellite imagery. The post Satellite Imagery Shows Iran’s Speedy Recovery After US Strikes: Report first appeared on Mediaite .",
   "source": "Mediaite (all)",
   "category": "mediaite_all",
   "published": "2026-06-01T13:36:49+00:00",
   "iran_topic": true
  },
  {
   "id": "a48727342133",
   "title": "5 minutes ago",
   "link": "https://bsky.app/profile/billcorbett.bsky.social/post/3mna6otnm4s26",
   "summary": "",
   "source": "@billcorbett",
   "category": "trump_bsky",
   "published": "2026-06-01T13:27:56.705+00:00",
   "iran_topic": false
  },
  {
   "id": "47468ecf63da",
   "title": "when you've lost Kat Cammack ...",
   "link": "https://bsky.app/profile/atrupar.com/post/3mna6l3ckem2c",
   "summary": "",
   "source": "@atrupar",
   "category": "trump_bsky",
   "published": "2026-06-01T13:25:50.505+00:00",
   "iran_topic": false
  },
  {
   "id": "269abc9eac52",
   "title": "NBC’s Craig Melvin Presses Jill Biden on Touting Joe’s Disaster Debate Performance Despite Private ‘Stroke’ Fear",
   "link": "https://www.mediaite.com/media/tv/nbcs-craig-melvin-presses-jill-biden-on-touting-joes-disaster-debate-performance-despite-private-stroke-fear/",
   "summary": "Melvin contrasted Jill Biden’s encouraging comments at a post-debate event with her newly admitted private concerns she says she had at the time. The post NBC’s Craig Melvin Presses Jill Biden on Touting Joe’s Disaster Debate Performance Despite Private ‘Stroke’ Fear first appeared on Mediaite .",
   "source": "Mediaite (all)",
   "category": "mediaite_all",
   "published": "2026-06-01T13:18:20+00:00",
   "iran_topic": false
  },
  {
   "id": "096768978892",
   "title": "Rep. Riley Moore on Iran: \"Of course it's another masterstroke by the president, who's ended multiple conflicts in his term. This is gonna be another one that's gonna go down in the history books as one of the great peace deals he's done.\"",
   "link": "https://bsky.app/profile/atrupar.com/post/3mna65duams2j",
   "summary": "",
   "source": "@atrupar",
   "category": "trump_bsky",
   "published": "2026-06-01T13:18:09.711+00:00",
   "iran_topic": true
  },
  {
   "id": "15c78c2cf888",
   "title": "“Donald Trump may be a showman, but he doesn’t really know how to put on a show — at least one that anyone but his most rabid supporters will want to attend (and even they’re getting tired).”",
   "link": "https://bsky.app/profile/oeishik.bsky.social/post/3mna5xi7uws2a",
   "summary": "",
   "source": "@oeishik",
   "category": "trump_bsky",
   "published": "2026-06-01T13:14:52.974+00:00",
   "iran_topic": false
  },
  {
   "id": "1276882fb719",
   "title": "New in PN: Trump's \"Freedom 250\" concert implodes spectacularly \"It was going to be so beautiful: A spectacular concert to celebrate 250 years of democracy, featuring some of the greatest musical acts this nation has produced. Okay, maybe not the greatest, but they were definitely musical acts!\"",
   "link": "https://bsky.app/profile/atrupar.com/post/3mna5qozqnc2y",
   "summary": "",
   "source": "@atrupar",
   "category": "trump_bsky",
   "published": "2026-06-01T13:11:05.234+00:00",
   "iran_topic": false
  },
  {
   "id": "759d177de116",
   "title": "‘You Had Me at Hello’: Bill Maher Fawns Over ‘Authentic’ Spencer Pratt in Podcast Appearance",
   "link": "https://www.mediaite.com/media/news/you-had-me-at-hello-bill-maher-fawns-over-authentic-spencer-pratt-in-podcast-appearance/",
   "summary": "Comedian and pundit Bill Maher lauded Los Angeles mayoral candidate Spencer Pratt as \"very authentic\" on Monday, praising the former reality TV star during a cozy podcast appearance. The post ‘You Had Me at Hello’: Bill Maher Fawns Over ‘Authentic’ Spencer Pratt in Podcast Appearance first appeared on Mediaite .",
   "source": "Mediaite (all)",
   "category": "mediaite_all",
   "published": "2026-06-01T12:45:03+00:00",
   "iran_topic": false
  },
  {
   "id": "ad7d62d70b7a",
   "title": "MAGA’s Dave Rubin Stumbles When Repeatedly Asked to Name Just One ‘Metric’ Trump’s Made ‘Better’ Since Taking Office",
   "link": "https://www.mediaite.com/media/tv/magas-dave-rubin-stumbles-when-repeatedly-asked-to-name-just-one-metric-trumps-made-better-since-taking-office/",
   "summary": "Rubin struggled to identify a single measurable economic improvement under Trump as a progressive debater repeatedly challenged him for data. The post MAGA’s Dave Rubin Stumbles When Repeatedly Asked to Name Just One ‘Metric’ Trump’s Made ‘Better’ Since Taking Office first appeared on Mediaite .",
   "source": "Mediaite (all)",
   "category": "mediaite_all",
   "published": "2026-06-01T12:23:29+00:00",
   "iran_topic": false
  },
  {
   "id": "6f52dc0aab06",
   "title": "CBS News Staff Sending Letter to CEO David Ellison Demanding He ‘Respect Editorial Values’ — Media Insider Tells MS NOW",
   "link": "https://www.mediaite.com/media/news/cbs-news-staff-sending-letter-to-ceo-david-ellison-demanding-he-respect-editorial-values-media-insider-tells-ms-now/",
   "summary": "CBS News staffers are reportedly sending a letter to Paramount CEO David Ellison demanding he \"respect editorial values\" — after the major '60 Minutes' shakeup. The post CBS News Staff Sending Letter to CEO David Ellison Demanding He ‘Respect Editorial Values’ — Media Insider Tells MS NOW first appeared on Mediaite .",
   "source": "Mediaite (all)",
   "category": "mediaite_all",
   "published": "2026-06-01T12:05:56+00:00",
   "iran_topic": false
  },
  {
   "id": "81579d2114f3",
   "title": "They know who their constituents are. It's definitely not us",
   "link": "https://bsky.app/profile/socialmedialab.ca/post/3mn7xhodogc2f",
   "summary": "",
   "source": "@socialmedialab",
   "category": "trump_bsky",
   "published": "2026-06-01T11:18:40.069+00:00",
   "iran_topic": false
  },
  {
   "id": "cf16e0cc7d70",
   "title": "UK’s Ban on Hasan Piker and Cenk Uygur Triggers Massive Online Meltdown From Left AND Right",
   "link": "https://www.mediaite.com/online/uks-ban-on-hasan-piker-and-cenk-uygur-triggers-massive-online-meltdown-from-left-and-right/",
   "summary": "British authorities revoked the travel authorizations of Piker and Uygur ahead of planned appearances at SXSW London, sparking tense debate online. The post UK’s Ban on Hasan Piker and Cenk Uygur Triggers Massive Online Meltdown From Left AND Right first appeared on Mediaite .",
   "source": "Mediaite (all)",
   "category": "mediaite_all",
   "published": "2026-06-01T11:14:25+00:00",
   "iran_topic": false
  },
  {
   "id": "7ea9604dd687",
   "title": "Trump's \"Freedom 250\" concert implodes spectacularly",
   "link": "https://www.publicnotice.co/p/trump-freedom-250",
   "summary": "His quest to dominate culture the way he dominates politics keeps going badly.",
   "source": "Rupar Public Notice",
   "category": "rupar_substack",
   "published": "2026-06-01T10:17:54+00:00",
   "iran_topic": false
  },
  {
   "id": "f08ac646f155",
   "title": "‘Sit Back and Relax’: Trump Rips ‘Unpatriotic Republicans,’ Democrats for Making His Iran Negotiations ‘MUCH Tougher’",
   "link": "https://www.mediaite.com/media/news/sit-back-and-relax-trump-rips-unpatriotic-republicans-democrats-for-making-his-iran-negotiations-much-tougher/",
   "summary": "The president hit out in a 1 a.m. ET Truth Social post urging lawmakers to “just sit back and relax” as he claimed that “it will all work out well in the end.” The post ‘Sit Back and Relax’: Trump Rips ‘Unpatriotic Republicans,’ Democrats for Making His Iran Negotiations ‘MUCH Tougher’ first appeared on Mediaite .",
   "source": "Mediaite (all)",
   "category": "mediaite_all",
   "published": "2026-06-01T10:14:21+00:00",
   "iran_topic": true
  },
  {
   "id": "ecc437273031",
   "title": "Did gowdy fall into a waffle iron",
   "link": "https://bsky.app/profile/unavaleable.bsky.social/post/3mn74lm6urs2p",
   "summary": "",
   "source": "@unavaleable",
   "category": "trump_bsky",
   "published": "2026-06-01T03:17:41.004+00:00",
   "iran_topic": false
  },
  {
   "id": "49d9a7b56320",
   "title": "Trey Gowdy always looks like he's still being born",
   "link": "https://bsky.app/profile/timprice.bsky.social/post/3mn73mcz2t22r",
   "summary": "",
   "source": "@timprice",
   "category": "trump_bsky",
   "published": "2026-06-01T03:00:11.189+00:00",
   "iran_topic": false
  },
  {
   "id": "6f48a6a4dc1b",
   "title": "Most incredible Colin Robinson vibes from this guy.",
   "link": "https://bsky.app/profile/goangelo.bsky.social/post/3mn6zy43ndk23",
   "summary": "",
   "source": "@goangelo",
   "category": "trump_bsky",
   "published": "2026-06-01T02:30:59.100+00:00",
   "iran_topic": false
  },
  {
   "id": "a59d87cb3826",
   "title": "Damn Beavis aged poorly",
   "link": "https://bsky.app/profile/onoshedidit.bsky.social/post/3mn6ykprpd223",
   "summary": "",
   "source": "@onoshedidit",
   "category": "trump_bsky",
   "published": "2026-06-01T02:05:36.244+00:00",
   "iran_topic": false
  },
  {
   "id": "21c9185a8b57",
   "title": "screencap is mine and is legit",
   "link": "https://bsky.app/profile/atrupar.com/post/3mn6xlehdys2y",
   "summary": "",
   "source": "@atrupar",
   "category": "trump_bsky",
   "published": "2026-06-01T01:48:04.183+00:00",
   "iran_topic": false
  },
  {
   "id": "b35da91dd7f8",
   "title": "there's playing the hits then there's running this chyron in May 2026",
   "link": "https://bsky.app/profile/atrupar.com/post/3mn6xf6dxnk2y",
   "summary": "",
   "source": "@atrupar",
   "category": "trump_bsky",
   "published": "2026-06-01T01:44:36.455+00:00",
   "iran_topic": false
  },
  {
   "id": "6cda69d8efdd",
   "title": "Full video from Scott MacFarlane here: youtu.be/nS-mgKx7LEk",
   "link": "https://bsky.app/profile/acyn.bsky.social/post/3mn6v2nastc25",
   "summary": "",
   "source": "@acyn",
   "category": "trump_bsky",
   "published": "2026-06-01T01:02:55.478+00:00",
   "iran_topic": false
  },
  {
   "id": "6062dc660dd2",
   "title": "MacFarlane: What the historic preservationists are arguing is that the Reflecting Pool is supposed to be the color it’s always been. It’s supposed to be what they call achromatic—no color. Because when it doesn’t have color, it does a better job of reflecting…",
   "link": "https://bsky.app/profile/acyn.bsky.social/post/3mn6v2naabk25",
   "summary": "",
   "source": "@acyn",
   "category": "trump_bsky",
   "published": "2026-06-01T01:02:55.477+00:00",
   "iran_topic": false
  },
  {
   "id": "a4aa7935b093",
   "title": "Trump Rages at CNN Over Report on Iran Deal — Wildly Claims ‘Even With New Ownership, It Is Unlikely to Ever Get Better!!!’",
   "link": "https://www.mediaite.com/politics/trump-trashes-cnn-over-iran-peace-deal-reports-even-with-new-ownership-it-is-unlikely-to-ever-get-better/",
   "summary": "Trump bashed CNN on Sunday for its reporting on his peace deal negotiations with Iran, saying it is no wonder the channel is a \"Low Ratings disaster\" The post Trump Rages at CNN Over Report on Iran Deal — Wildly Claims ‘Even With New Ownership, It Is Unlikely to Ever Get Better!!!’ first appeared on Mediaite .",
   "source": "Mediaite (all)",
   "category": "mediaite_all",
   "published": "2026-06-01T00:51:04+00:00",
   "iran_topic": true
  },
  {
   "id": "fdc1874c5e04",
   "title": "Trump's Justice Department is seeking the names, addresses, and banking information of Reddit and X users — ratcheting up efforts to identify social media critics of government deportation efforts. Jeanine Pirro's office has subpoenaed the social media companies as part of criminal investigations.",
   "link": "https://bsky.app/profile/kylegriffin1.bsky.social/post/3mn6truoh222o",
   "summary": "",
   "source": "@kylegriffin1",
   "category": "trump_bsky",
   "published": "2026-06-01T00:40:07.552+00:00",
   "iran_topic": false
  },
  {
   "id": "cb2a25fb414d",
   "title": "Graham Platner Blasts ‘Establishment Media’ for Trying to ‘Rip Apart’ His Loving Marriage",
   "link": "https://www.mediaite.com/media/news/graham-platner-blasts-establishment-media-for-trying-to-rip-apart-his-loving-marriage/",
   "summary": "Graham Platner accused the \"establishment media\" of \"journalistic malpractice\" for running stories that his wife told campaign officials about his sexting. The post Graham Platner Blasts ‘Establishment Media’ for Trying to ‘Rip Apart’ His Loving Marriage first appeared on Mediaite .",
   "source": "Mediaite (all)",
   "category": "mediaite_all",
   "published": "2026-06-01T00:09:51+00:00",
   "iran_topic": false
  },
  {
   "id": "f2d793f37746",
   "title": "Hasan Piker and The Young Turks’ Cenk Uygur Banned From Entering United Kingdom",
   "link": "https://www.mediaite.com/media/the-young-turks-cenk-uygur-banned-from-entering-united-kingdom/",
   "summary": "The Young Turks' Cenk Uygur was barred from entering the United Kingdom over government concerns his presence would not be “conducive to the public good\" The post Hasan Piker and The Young Turks’ Cenk Uygur Banned From Entering United Kingdom first appeared on Mediaite .",
   "source": "Mediaite (all)",
   "category": "mediaite_all",
   "published": "2026-05-31T23:43:52+00:00",
   "iran_topic": false
  },
  {
   "id": "8c6891478cb7",
   "title": "old man is ranting about imaginary deals again",
   "link": "https://bsky.app/profile/atrupar.com/post/3mn6qeqziws24",
   "summary": "",
   "source": "@atrupar",
   "category": "trump_bsky",
   "published": "2026-05-31T23:39:06.284+00:00",
   "iran_topic": false
  },
  {
   "id": "a7d71c23001e",
   "title": "Nick Shirley Slams ‘Left-Wing Media’ for Putting ‘Target’ on His Back Over Minnesota Fraud Reporting",
   "link": "https://www.mediaite.com/media/nick-shirley-slams-left-wing-media-for-putting-target-on-his-back-over-minnesota-fraud-reporting/",
   "summary": "Nick Shirley said it's too risky for him to report on certain topics now because the \"left-wing media\" put a \"target\" on his back following his Minnesota report The post Nick Shirley Slams ‘Left-Wing Media’ for Putting ‘Target’ on His Back Over Minnesota Fraud Reporting first appeared on Mediaite .",
   "source": "Mediaite (all)",
   "category": "mediaite_all",
   "published": "2026-05-31T22:57:51+00:00",
   "iran_topic": false
  },
  {
   "id": "49c6e5a5c10d",
   "title": "Khanna: We need to be taxing agentic AI more than we are taxing human workers.",
   "link": "https://bsky.app/profile/acyn.bsky.social/post/3mn6m24usol2y",
   "summary": "",
   "source": "@acyn",
   "category": "trump_bsky",
   "published": "2026-05-31T22:21:34.367+00:00",
   "iran_topic": false
  },
  {
   "id": "5b02c324f701",
   "title": "Reid: They want affection from us. They want all the stars to show up for America 250. They want all their favorite Black celebrities to sing and dance for them. But they hate Black and Brown people.",
   "link": "https://bsky.app/profile/acyn.bsky.social/post/3mn6ljmzzsv2y",
   "summary": "",
   "source": "@acyn",
   "category": "trump_bsky",
   "published": "2026-05-31T22:12:20.867+00:00",
   "iran_topic": false
  },
  {
   "id": "7bd849d1dd72",
   "title": "CNN Medical Expert Trolls Trump for Claiming ‘Cognitive Test’ Shows ‘Extreme Intelligence’: ‘It’s a Dementia Screening Tool’",
   "link": "https://www.mediaite.com/media/news/cnn-medical-expert-trolls-trump-for-claiming-cognitive-test-shows-extreme-intelligence-its-a-dementia-screening-tool/",
   "summary": "Dr. Jonathan Reiner trolled Donald Trump on Sunday after the president once again bragged that his \"cognitive test\" showed \"extreme intelligence.\" The post CNN Medical Expert Trolls Trump for Claiming ‘Cognitive Test’ Shows ‘Extreme Intelligence’: ‘It’s a Dementia Screening Tool’ first appeared on Mediaite .",
   "source": "Mediaite (all)",
   "category": "mediaite_all",
   "published": "2026-05-31T22:07:18+00:00",
   "iran_topic": false
  },
  {
   "id": "f9289fc1c1b1",
   "title": "Thanks much Mike!",
   "link": "https://bsky.app/profile/atrupar.com/post/3mn6kwro4bs2y",
   "summary": "",
   "source": "@atrupar",
   "category": "trump_bsky",
   "published": "2026-05-31T22:01:48.492+00:00",
   "iran_topic": false
  },
  {
   "id": "55d6a29a8064",
   "title": "Reid: They’re whiny little bitches. If you say Stephen Miller is ugly—which is a fact—they cry. They want to be treated as children. They want to be praised.",
   "link": "https://bsky.app/profile/acyn.bsky.social/post/3mn6kulg2vb23",
   "summary": "",
   "source": "@acyn",
   "category": "trump_bsky",
   "published": "2026-05-31T22:00:34.535+00:00",
   "iran_topic": false
  },
  {
   "id": "e0e6c7623610",
   "title": "The Jeffrey Epstein and The Donald J Trump Memorial Bunker",
   "link": "https://bsky.app/profile/coachfinstock.bsky.social/post/3mn6jhn3o2k2p",
   "summary": "",
   "source": "@coachfinstock",
   "category": "trump_bsky",
   "published": "2026-05-31T21:35:26.631+00:00",
   "iran_topic": false
  },
  {
   "id": "814e55ea293e",
   "title": "Ossoff: This is what small men like Donald Trump and JD Vance and Stephen Miller will never understand—that our national greatness flows not through our blood or our genes, but through our ideas.",
   "link": "https://bsky.app/profile/acyn.bsky.social/post/3mn6iznali423",
   "summary": "",
   "source": "@acyn",
   "category": "trump_bsky",
   "published": "2026-05-31T21:27:36.895+00:00",
   "iran_topic": false
  },
  {
   "id": "b0f689f18013",
   "title": "Ossoff: They tried to run Kemp, but he refused. So we're left with the congressman who's only a congressman because his daddy was a congressman and the coach, who's only a coach because his daddy was a coach.",
   "link": "https://bsky.app/profile/acyn.bsky.social/post/3mn6ij6uhnc2n",
   "summary": "",
   "source": "@acyn",
   "category": "trump_bsky",
   "published": "2026-05-31T21:18:24.960+00:00",
   "iran_topic": false
  },
  {
   "id": "88ebe9b946c3",
   "title": "“donald trump’s brownshirts” Ossoff going way harder than i expected wow",
   "link": "https://bsky.app/profile/somearelakes.bsky.social/post/3mn6i55lzts2h",
   "summary": "",
   "source": "@somearelakes",
   "category": "trump_bsky",
   "published": "2026-05-31T21:11:41.107+00:00",
   "iran_topic": false
  },
  {
   "id": "fe830d5e9daa",
   "title": "Ossoff: The America first president who said he would end foreign wars to put America first and focus on America's working class. Instead, now he says, it's not possible for us to take care of daycare, Medicaid or Medicare. Now he says all we can afford is war.",
   "link": "https://bsky.app/profile/acyn.bsky.social/post/3mn6hzqu4in23",
   "summary": "",
   "source": "@acyn",
   "category": "trump_bsky",
   "published": "2026-05-31T21:09:46.942+00:00",
   "iran_topic": false
  },
  {
   "id": "221558b14a0e",
   "title": "Ossoff: He promised the golden age. Inflation's higher than when Trump took office. Unemployment's higher than when Trump took office, and consumer sentiments at its worst in 70 years.",
   "link": "https://bsky.app/profile/acyn.bsky.social/post/3mn6huzommy2r",
   "summary": "",
   "source": "@acyn",
   "category": "trump_bsky",
   "published": "2026-05-31T21:07:08.437+00:00",
   "iran_topic": false
  },
  {
   "id": "f98672b133d2",
   "title": "Ossoff: The president promised to fight for the working class and end foreign wars. Instead, he cut your healthcare to give the rich another tax break and last week yet more Americans were wounded in a war no one voted for and no one can explain",
   "link": "https://bsky.app/profile/acyn.bsky.social/post/3mn6hpjdaqv2r",
   "summary": "",
   "source": "@acyn",
   "category": "trump_bsky",
   "published": "2026-05-31T21:04:03.514+00:00",
   "iran_topic": false
  },
  {
   "id": "aefe2fff2833",
   "title": "\"He's doing these things now because no one will honor him when he's gone\" is a very good line of attack against Trump.",
   "link": "https://bsky.app/profile/brooklynspoke.bsky.social/post/3mn6hpdvswc2a",
   "summary": "",
   "source": "@brooklynspoke",
   "category": "trump_bsky",
   "published": "2026-05-31T21:03:57.957+00:00",
   "iran_topic": false
  },
  {
   "id": "f6d24fdb76ef",
   "title": "Ossoff: While you pay more for everything, Trump wants your tax dollars for what many are calling the Jeffrey Epstein Memorial Ballroom. He forced out that Republican, the one who made him release the Epstein files. That is true commitment to the cover-up.",
   "link": "https://bsky.app/profile/acyn.bsky.social/post/3mn6hmn6ki52i",
   "summary": "",
   "source": "@acyn",
   "category": "trump_bsky",
   "published": "2026-05-31T21:02:26.892+00:00",
   "iran_topic": false
  },
  {
   "id": "5770534c5285",
   "title": "Ossoff: He’s trying to put his face on the money. He's building a monument to himself . But see, Atlanta, he's doing these things now because no one will honor him when he’s gone… because he's a failed president and a national disgrace.",
   "link": "https://bsky.app/profile/acyn.bsky.social/post/3mn6hjd5nam27",
   "summary": "",
   "source": "@acyn",
   "category": "trump_bsky",
   "published": "2026-05-31T21:00:35.697+00:00",
   "iran_topic": false
  },
  {
   "id": "501533fe8ffa",
   "title": "Ossoff: He settled the suit with himself to create a $1.8 billion slush fund so he can cut checks to cronies and Jan 6th foot soldiers. The same men who sacked the Capitol. Donald Trump's brown shirts . He pardoned them, and now he wants you to pay them.",
   "link": "https://bsky.app/profile/acyn.bsky.social/post/3mn6hhrmrfq23",
   "summary": "",
   "source": "@acyn",
   "category": "trump_bsky",
   "published": "2026-05-31T20:59:43.776+00:00",
   "iran_topic": false
  },
  {
   "id": "7a27bf4fec3a",
   "title": "Heads up: Trump's FBI in recent weeks has interviewed current and former election officials about the 2020 election in Milwaukee. Election officials are cautiously watching the developments in Milwaukee to see if agents try to seize ballots — as they did in Fulton County.",
   "link": "https://bsky.app/profile/kylegriffin1.bsky.social/post/3mn6ftgbxek2s",
   "summary": "",
   "source": "@kylegriffin1",
   "category": "trump_bsky",
   "published": "2026-05-31T20:30:27.187+00:00",
   "iran_topic": false
  },
  {
   "id": "186afccf9961",
   "title": "Mike Pence to NBC on Trump's slush fund: \"It's a bad idea from the start. And I would encourage the administration just to drop it ... It's deeply offensive to me that you could have a fund that could even possibly compensate people who assaulted police officers or vandalized the Capitol on Jan. 6.\"",
   "link": "https://bsky.app/profile/kylegriffin1.bsky.social/post/3mn6chp6bo22s",
   "summary": "",
   "source": "@kylegriffin1",
   "category": "trump_bsky",
   "published": "2026-05-31T19:30:12.625+00:00",
   "iran_topic": false
  }
 ]
}